geoclient
