Metadata-Version: 2.1
Name: python-geoclient
Version: 0.1.1
Summary: Python wrapper for the NYC Geoclient RESTful API
Home-page: http://github.com/ishiland/python-geoclient
Author: Ian Shiland, John Krauss
Author-email: ishiland@gmail.com
License: BSD
Keywords: NYC,geocoder,python-geoclient,geoclient
Platform: UNKNOWN
Classifier: Development Status :: 4 - Beta
Classifier: Topic :: Software Development
Classifier: Natural Language :: English
Classifier: License :: OSI Approved :: BSD License
Classifier: Programming Language :: Python :: 2.7
Classifier: Programming Language :: Python :: 3.4
Classifier: Programming Language :: Python :: 3.5
Classifier: Programming Language :: Python :: 3.6
Classifier: Programming Language :: Python :: 3.7
Provides-Extra: dev
